banrural_bank_gt/__init__.py
banrural_bank_gt/models.py
banrural_bank_parser_gt-0.4.4.dist-info/METADATA
banrural_bank_parser_gt-0.4.4.dist-info/WHEEL
banrural_bank_parser_gt-0.4.4.dist-info/top_level.txt
banrural_bank_parser_gt-0.4.4.dist-info/RECORD
